<?xml version="1.0"?>
<!--
~ Licensed under the Apache License, Version 2.0 (the "License");
~ you may not use this file except in compliance with the License.
~ You may obtain a copy of the License at
~
~   http://www.apache.org/licenses/LICENSE-2.0
~
~ Unless required by applicable law or agreed to in writing, software
~ distributed under the License is distributed on an "AS IS" BASIS,
~ WITHOUT WARRANTIES OR CONDITIONS OF ANY KIND, either express or implied.
~ See the License for the specific language governing permissions and
~ limitations under the License.
-->
<!DOCTYPE Configure PUBLIC "-//Jetty//Configure//EN" "http://www.eclipse.org/jetty/configure_9_0.dtd">
<!-- ============================================================= -->
<!-- Configure the Http Configuration -->
<!-- ============================================================= -->
<Configure id="httpConfig" class="org.eclipse.jetty.server.HttpConfiguration">
	<Set name="secureScheme">https</Set>
	<Set name="securePort"><Property name="jetty.maven.plugin.port" default="58080" /></Set>
	<Set name="outputBufferSize">32768</Set>
	<Set name="requestHeaderSize">8192</Set>
	<Set name="responseHeaderSize">8192</Set>
	<Set name="sendServerVersion">true</Set>
	<Set name="sendDateHeader">false</Set>
	<Set name="headerCacheSize">512</Set>
</Configure>
